[
  {
    "id": 303185071,
    "slotType": 17,
    "inventoryType": 2,
    "gainType": 0,
    "icon": "GUI/Icon/Item/Costume/PC_J/PC_J_EQ_Swimming4_Costume01_07.png",
    "class": 10
  },
  {
    "id": 303185081,
    "slotType": 22,
    "inventoryType": 2,
    "gainType": 0,
    "icon": "GUI/Icon/Item/Costume/PC_J/PC_J_EQ_Swimming4_Costume02_08.png",
    "class": 10
  },
  {
    "id": 303185051,
    "slotType": 15,
    "inventoryType": 2,
    "gainType": 0,
    "icon": "GUI/Icon/Item/Costume/PC_J/PC_J_EQ_Swimming4_glove_05.png",
    "class": 10
  },
  {
    "id": 303185121,
    "slotType": 20,
    "inventoryType": 2,
    "gainType": 0,
    "icon": "GUI/Icon/Item/Costume/PC_J/PC_J_EQ_Swimming4_Shoes_12.png",
    "class": 10
  },
  {
    "id": 903185021,
    "slotType": 0,
    "inventoryType": 13,
    "gainType": 0,
    "icon": "GUI/Icon/Item/Function/Package/PackageBox.png",
    "class": 10
  },
  {
    "id": 903185071,
    "slotType": 0,
    "inventoryType": 13,
    "gainType": 0,
    "icon": "GUI/Icon/Item/Function/Package/PackageBox.png",
    "class": 10
  },
  {
    "id": 903185081,
    "slotType": 0,
    "inventoryType": 13,
    "gainType": 0,
    "icon": "GUI/Icon/Item/Function/Package/PackageBox.png",
    "class": 10
  },
  {
    "id": 903185051,
    "slotType": 0,
    "inventoryType": 13,
    "gainType": 0,
    "icon": "GUI/Icon/Item/Function/Package/PackageBox.png",
    "class": 10
  },
  {
    "id": 903185121,
    "slotType": 0,
    "inventoryType": 13,
    "gainType": 0,
    "icon": "GUI/Icon/Item/Function/Package/PackageBox.png",
    "class": 10
  },
  {
    "id": 903185072,
    "slotType": 0,
    "inventoryType": 13,
    "gainType": 0,
    "icon": "GUI/Icon/Item/Function/Package/ETC_0_DyeCostumePackage_PC_J.png",
    "class": 10
  },
  {
    "id": 1003185072,
    "slotType": 0,
    "inventoryType": 13,
    "gainType": 0,
    "icon": "GUI/Icon/Item/Function/Package/ETC_0_DyeCostumePackage_PC_J.png",
    "class": 10
  },
  {
    "id": 903185073,
    "slotType": 0,
    "inventoryType": 13,
    "gainType": 0,
    "icon": "GUI/Icon/Item/Function/Package/ETC_0_DyeCostumePackage_PC_J.png",
    "class": 10
  },
  {
    "id": 899000030,
    "slotType": 0,
    "inventoryType": 13,
    "gainType": 0,
    "icon": "GUI/Icon/Item/Cash/ETC_0_CashPhotoAlbum.png",
    "class": 10
  },
  {
    "id": 906081349,
    "slotType": 0,
    "inventoryType": 0,
    "gainType": 0,
    "icon": "GUI/Icon/Item/Etc/ETC_0_TitleItem.png",
    "class": 0
  },
  {
    "id": 906081350,
    "slotType": 0,
    "inventoryType": 0,
    "gainType": 0,
    "icon": "GUI/Icon/Item/Etc/ETC_0_TitleItem.png",
    "class": 0
  },
  {
    "id": 906081351,
    "slotType": 0,
    "inventoryType": 0,
    "gainType": 0,
    "icon": "GUI/Icon/Item/Etc/ETC_0_TitleItem.png",
    "class": 0
  },
  {
    "id": 906081352,
    "slotType": 0,
    "inventoryType": 0,
    "gainType": 0,
    "icon": "GUI/Icon/Item/Etc/ETC_0_TitleItem.png",
    "class": 0
  },
  {
    "id": 906081353,
    "slotType": 0,
    "inventoryType": 0,
    "gainType": 0,
    "icon": "GUI/Icon/Item/Function/Package/PackageBox.png",
    "class": 0
  },
  {
    "id": 480004023,
    "slotType": 0,
    "inventoryType": 13,
    "gainType": 0,
    "icon": "GUI/Icon/Item/Function/Package/PackageBox.png",
    "class": 0
  },
  {
    "id": 837200236,
    "slotType": 0,
    "inventoryType": 13,
    "gainType": 0,
    "icon": "GUI/Icon/Item/Cash/ETC_0_AkashicRecordTransfer.png",
    "class": 0
  },
  {
    "id": 1230711072,
    "slotType": 0,
    "inventoryType": 13,
    "gainType": 0,
    "icon": "GUI/Icon/Item/Function/Package/PackageBox.png",
    "class": 0
  },
  {
    "id": 1230711073,
    "slotType": 0,
    "inventoryType": 13,
    "gainType": 0,
    "icon": "GUI/Icon/Item/Function/Package/PackageBox.png",
    "class": 0
  },
  {
    "id": 839500023,
    "slotType": 251,
    "inventoryType": 13,
    "gainType": 0,
    "icon": "GUI/Icon/Item/Costume/PC_J/PC_J_EQ_CashHair19_Hair_32.png",
    "class": 10
  },
  {
    "id": 906081354,
    "slotType": 0,
    "inventoryType": 0,
    "gainType": 2,
    "icon": "GUI/Icon/Item/Event/Event_GrutonWaterBattle.png",
    "class": 0
  },
  {
    "id": 906081355,
    "slotType": 0,
    "inventoryType": 0,
    "gainType": 0,
    "icon": "GUI/Icon/Item/Consumption/Buff/Con_0_HawkPerfume.png",
    "class": 0
  },
  {
    "id": 906081356,
    "slotType": 0,
    "inventoryType": 13,
    "gainType": 0,
    "icon": "GUI/Icon/Item/Cash/QBD.png",
    "class": 0
  },
  {
    "id": 2003170102,
    "slotType": 17,
    "inventoryType": 2,
    "gainType": 0,
    "icon": "",
    "class": 1
  },
  {
    "id": 2003170202,
    "slotType": 17,
    "inventoryType": 2,
    "gainType": 0,
    "icon": "",
    "class": 2
  },
  {
    "id": 2003170302,
    "slotType": 17,
    "inventoryType": 2,
    "gainType": 0,
    "icon": "",
    "class": 3
  },
  {
    "id": 2003170402,
    "slotType": 17,
    "inventoryType": 2,
    "gainType": 0,
    "icon": "",
    "class": 4
  },
  {
    "id": 2003170502,
    "slotType": 17,
    "inventoryType": 2,
    "gainType": 0,
    "icon": "",
    "class": 5
  },
  {
    "id": 2003170602,
    "slotType": 17,
    "inventoryType": 2,
    "gainType": 0,
    "icon": "",
    "class": 6
  },
  {
    "id": 2003170702,
    "slotType": 17,
    "inventoryType": 2,
    "gainType": 0,
    "icon": "",
    "class": 7
  },
  {
    "id": 2003170802,
    "slotType": 17,
    "inventoryType": 2,
    "gainType": 0,
    "icon": "",
    "class": 8
  },
  {
    "id": 2003170902,
    "slotType": 17,
    "inventoryType": 2,
    "gainType": 0,
    "icon": "",
    "class": 9
  },
  {
    "id": 2003171002,
    "slotType": 17,
    "inventoryType": 2,
    "gainType": 0,
    "icon": "",
    "class": 10
  },
  {
    "id": 211005143,
    "slotType": 21,
    "inventoryType": 2,
    "gainType": 0,
    "icon": "",
    "class": 0
  },
  {
    "id": 211005144,
    "slotType": 21,
    "inventoryType": 2,
    "gainType": 0,
    "icon": "",
    "class": 0
  },
  {
    "id": 211005145,
    "slotType": 21,
    "inventoryType": 2,
    "gainType": 0,
    "icon": "",
    "class": 0
  },
  {
    "id": 211005146,
    "slotType": 21,
    "inventoryType": 2,
    "gainType": 0,
    "icon": "",
    "class": 0
  },
  {
    "id": 211005147,
    "slotType": 21,
    "inventoryType": 2,
    "gainType": 0,
    "icon": "",
    "class": 0
  },
  {
    "id": 211005148,
    "slotType": 21,
    "inventoryType": 2,
    "gainType": 0,
    "icon": "",
    "class": 0
  },
  {
    "id": 211005149,
    "slotType": 21,
    "inventoryType": 2,
    "gainType": 0,
    "icon": "",
    "class": 0
  },
  {
    "id": 211005150,
    "slotType": 21,
    "inventoryType": 2,
    "gainType": 0,
    "icon": "",
    "class": 0
  },
  {
    "id": 211005151,
    "slotType": 21,
    "inventoryType": 2,
    "gainType": 0,
    "icon": "",
    "class": 0
  },
  {
    "id": 211005152,
    "slotType": 21,
    "inventoryType": 2,
    "gainType": 0,
    "icon": "",
    "class": 0
  },
  {
    "id": 211005153,
    "slotType": 0,
    "inventoryType": 0,
    "gainType": 1,
    "icon": "GUI/Icon/Item/Consumption/Cure/HP_1.png",
    "class": 0
  },
  {
    "id": 211005154,
    "slotType": 0,
    "inventoryType": 0,
    "gainType": 1,
    "icon": "GUI/Icon/Item/Consumption/Cure/HP_1.png",
    "class": 0
  },
  {
    "id": 211005155,
    "slotType": 0,
    "inventoryType": 0,
    "gainType": 1,
    "icon": "GUI/Icon/Item/Consumption/Cure/HP_1.png",
    "class": 0
  },
  {
    "id": 211005156,
    "slotType": 0,
    "inventoryType": 0,
    "gainType": 1,
    "icon": "GUI/Icon/Item/Consumption/Cure/HP_1.png",
    "class": 0
  },
  {
    "id": 906071005,
    "slotType": 0,
    "inventoryType": 0,
    "gainType": 0,
    "icon": "GUI/Icon/Item/Function/Package/RandomBox.png",
    "class": 0
  },
  {
    "id": 460401000,
    "slotType": 0,
    "inventoryType": 0,
    "gainType": 1,
    "icon": "GUI/Pet/fragment/Icon_Pet_fragment_4010.png",
    "class": 0
  },
  {
    "id": 460401031,
    "slotType": 220,
    "inventoryType": 13,
    "gainType": 0,
    "icon": "GUI/Pet/Box_Image/Box_Image_4010.png",
    "class": 0
  },
  {
    "id": 461401001,
    "slotType": 0,
    "inventoryType": 13,
    "gainType": 0,
    "icon": "GUI/Pet/fragment/Icon_Pet_fragment_4010.png",
    "class": 0
  },
  {
    "id": 461401002,
    "slotType": 0,
    "inventoryType": 13,
    "gainType": 0,
    "icon": "GUI/Pet/Box_Image/Icon_Pet_fragment_4010_3.png",
    "class": 0
  },
  {
    "id": 461401003,
    "slotType": 0,
    "inventoryType": 13,
    "gainType": 0,
    "icon": "GUI/Pet/Box_Image/Icon_Pet_fragment_4010_5.png",
    "class": 0
  },
  {
    "id": 906081357,
    "slotType": 0,
    "inventoryType": 0,
    "gainType": 0,
    "icon": "GUI/Icon/Item/Etc/ETC_0_TitleItem.png",
    "class": 0
  },
  {
    "id": 906081358,
    "slotType": 0,
    "inventoryType": 0,
    "gainType": 0,
    "icon": "GUI/Icon/Item/Etc/ETC_0_TitleItem.png",
    "class": 0
  },
  {
    "id": 906081359,
    "slotType": 0,
    "inventoryType": 13,
    "gainType": 0,
    "icon": "GUI/Icon/Item/Function/Package/PackageBox.png",
    "class": 0
  },
  {
    "id": 906081360,
    "slotType": 0,
    "inventoryType": 0,
    "gainType": 0,
    "icon": "GUI/Icon/Item/Event/Event_Old_Mail.png",
    "class": 0
  },
  {
    "id": 480004024,
    "slotType": 0,
    "inventoryType": 13,
    "gainType": 0,
    "icon": "GUI/Icon/Item/Function/Package/PackageBox.png",
    "class": 0
  },
  {
    "id": 837200237,
    "slotType": 0,
    "inventoryType": 13,
    "gainType": 0,
    "icon": "GUI/Icon/Item/Cash/ETC_0_AkashicRecordTransfer.png",
    "class": 0
  },
  {
    "id": 1230711074,
    "slotType": 0,
    "inventoryType": 13,
    "gainType": 0,
    "icon": "GUI/Icon/Item/Function/Package/PackageBox.png",
    "class": 0
  },
  {
    "id": 1230711075,
    "slotType": 0,
    "inventoryType": 13,
    "gainType": 0,
    "icon": "GUI/Icon/Item/Function/Package/PackageBox.png",
    "class": 0
  },
  {
    "id": 150822002,
    "slotType": 0,
    "inventoryType": 0,
    "gainType": 0,
    "icon": "GUI/Icon/Item/Familiar/GearFamiliar_Type_I_2.png",
    "class": 0
  },
  {
    "id": 150822003,
    "slotType": 0,
    "inventoryType": 0,
    "gainType": 0,
    "icon": "GUI/Icon/Item/Familiar/GearFamiliar_Type_J_2.png",
    "class": 0
  },
  {
    "id": 150822004,
    "slotType": 0,
    "inventoryType": 0,
    "gainType": 0,
    "icon": "GUI/Icon/Item/Familiar/GearFamiliar_Type_K_2.png",
    "class": 0
  },
  {
    "id": 150822005,
    "slotType": 0,
    "inventoryType": 0,
    "gainType": 0,
    "icon": "GUI/Icon/Item/Familiar/GearFamiliar_Type_L_2.png",
    "class": 0
  },
  {
    "id": 150823002,
    "slotType": 0,
    "inventoryType": 0,
    "gainType": 0,
    "icon": "GUI/Icon/Item/Familiar/GearFamiliar_Type_I.png",
    "class": 0
  },
  {
    "id": 150823003,
    "slotType": 0,
    "inventoryType": 0,
    "gainType": 0,
    "icon": "GUI/Icon/Item/Familiar/GearFamiliar_Type_J.png",
    "class": 0
  },
  {
    "id": 150823004,
    "slotType": 0,
    "inventoryType": 0,
    "gainType": 0,
    "icon": "GUI/Icon/Item/Familiar/GearFamiliar_Type_K.png",
    "class": 0
  },
  {
    "id": 150823005,
    "slotType": 0,
    "inventoryType": 0,
    "gainType": 0,
    "icon": "GUI/Icon/Item/Familiar/GearFamiliar_Type_L.png",
    "class": 0
  },
  {
    "id": 720102105,
    "slotType": 0,
    "inventoryType": 0,
    "gainType": 0,
    "icon": "GUI/Icon/Item/Familiar/AssaultFamiliar_Core_1.png",
    "class": 0
  },
  {
    "id": 720102106,
    "slotType": 0,
    "inventoryType": 0,
    "gainType": 0,
    "icon": "GUI/Icon/Item/Etc/GaluxyCube15.png",
    "class": 0
  },
  {
    "id": 906081361,
    "slotType": 0,
    "inventoryType": 0,
    "gainType": 0,
    "icon": "GUI/Icon/Item/Consumption/Buff/GloryPerfume.png",
    "class": 0
  },
  {
    "id": 906078107,
    "slotType": 0,
    "inventoryType": 0,
    "gainType": 0,
    "icon": "GUI/Icon/Item/Function/Package/ETC_0_CostumePackage.png",
    "class": 0
  },
  {
    "id": 906078108,
    "slotType": 0,
    "inventoryType": 0,
    "gainType": 0,
    "icon": "GUI/Icon/Item/Function/Package/ETC_0_CostumePackage_PC_A.png",
    "class": 1
  },
  {
    "id": 906078109,
    "slotType": 0,
    "inventoryType": 0,
    "gainType": 0,
    "icon": "GUI/Icon/Item/Function/Package/ETC_0_CostumePackage_PC_B.png",
    "class": 2
  },
  {
    "id": 906078110,
    "slotType": 0,
    "inventoryType": 0,
    "gainType": 0,
    "icon": "GUI/Icon/Item/Function/Package/ETC_0_CostumePackage_PC_C.png",
    "class": 3
  },
  {
    "id": 906078111,
    "slotType": 0,
    "inventoryType": 0,
    "gainType": 0,
    "icon": "GUI/Icon/Item/Function/Package/ETC_0_CostumePackage_PC_D.png",
    "class": 4
  },
  {
    "id": 906078112,
    "slotType": 0,
    "inventoryType": 0,
    "gainType": 0,
    "icon": "GUI/Icon/Item/Function/Package/ETC_0_CostumePackage_PC_E.png",
    "class": 5
  },
  {
    "id": 906078113,
    "slotType": 0,
    "inventoryType": 0,
    "gainType": 0,
    "icon": "GUI/Icon/Item/Function/Package/ETC_0_CostumePackage_PC_F.png",
    "class": 6
  },
  {
    "id": 906078114,
    "slotType": 0,
    "inventoryType": 0,
    "gainType": 0,
    "icon": "GUI/Icon/Item/Function/Package/ETC_0_CostumePackage_PC_G.png",
    "class": 7
  },
  {
    "id": 906078115,
    "slotType": 0,
    "inventoryType": 0,
    "gainType": 0,
    "icon": "GUI/Icon/Item/Function/Package/ETC_0_CostumePackage_PC_H.png",
    "class": 8
  },
  {
    "id": 906078116,
    "slotType": 0,
    "inventoryType": 0,
    "gainType": 0,
    "icon": "GUI/Icon/Item/Function/Package/ETC_0_CostumePackage_PC_I.png",
    "class": 9
  },
  {
    "id": 906078117,
    "slotType": 0,
    "inventoryType": 0,
    "gainType": 0,
    "icon": "GUI/Icon/Item/Function/Package/ETC_0_CostumePackage_PC_J.png",
    "class": 10
  },
  {
    "id": 201666071,
    "slotType": 17,
    "inventoryType": 2,
    "gainType": 0,
    "icon": "GUI/Icon/Item/Costume/PC_A/PC_A_EQ_SpringCasual3_Costume01_07.png",
    "class": 1
  },
  {
    "id": 201666081,
    "slotType": 22,
    "inventoryType": 2,
    "gainType": 0,
    "icon": "GUI/Icon/Item/Costume/PC_A/PC_A_EQ_SpringCasual3_Costume02_08.png",
    "class": 1
  },
  {
    "id": 201666101,
    "slotType": 18,
    "inventoryType": 2,
    "gainType": 0,
    "icon": "GUI/Icon/Item/Costume/PC_A/PC_A_EQ_SpringCasual3_back_10.png",
    "class": 1
  },
  {
    "id": 201666111,
    "slotType": 19,
    "inventoryType": 2,
    "gainType": 0,
    "icon": "GUI/Icon/Item/Costume/PC_A/PC_A_EQ_SpringCasual3_Socks_11.png",
    "class": 1
  },
  {
    "id": 201666121,
    "slotType": 20,
    "inventoryType": 2,
    "gainType": 0,
    "icon": "GUI/Icon/Item/Costume/PC_A/PC_A_EQ_SpringCasual3_Shoes_12.png",
    "class": 1
  },
  {
    "id": 801666072,
    "slotType": 0,
    "inventoryType": 13,
    "gainType": 0,
    "icon": "GUI/Icon/Item/Function/Package/ETC_0_CostumePackage_PC_A.png",
    "class": 1
  },
  {
    "id": 292503021,
    "slotType": 12,
    "inventoryType": 2,
    "gainType": 0,
    "icon": "GUI/Icon/Item/Costume/PC_I/PC_I_EQ_GlutonHat_HairAcc01_01.png",
    "class": 9
  },
  {
    "id": 202503021,
    "slotType": 12,
    "inventoryType": 2,
    "gainType": 0,
    "icon": "GUI/Icon/Item/Costume/PC_J/PC_J_EQ_GlutonHat_HairAcc01_01.png",
    "class": 10
  },
  {
    "id": 812503022,
    "slotType": 0,
    "inventoryType": 13,
    "gainType": 0,
    "icon": "GUI/Icon/Item/Function/Package/ETC_0_CostumePackage_PC_A.png",
    "class": 0
  },
  {
    "id": 822503022,
    "slotType": 0,
    "inventoryType": 13,
    "gainType": 0,
    "icon": "GUI/Icon/Item/Function/Package/ETC_0_CostumePackage_PC_B.png",
    "class": 0
  },
  {
    "id": 832503022,
    "slotType": 0,
    "inventoryType": 13,
    "gainType": 0,
    "icon": "GUI/Icon/Item/Function/Package/ETC_0_CostumePackage_PC_C.png",
    "class": 0
  },
  {
    "id": 842503022,
    "slotType": 0,
    "inventoryType": 13,
    "gainType": 0,
    "icon": "GUI/Icon/Item/Function/Package/ETC_0_CostumePackage_PC_D.png",
    "class": 0
  },
  {
    "id": 852503022,
    "slotType": 0,
    "inventoryType": 13,
    "gainType": 0,
    "icon": "GUI/Icon/Item/Function/Package/ETC_0_CostumePackage_PC_E.png",
    "class": 0
  },
  {
    "id": 862503022,
    "slotType": 0,
    "inventoryType": 13,
    "gainType": 0,
    "icon": "GUI/Icon/Item/Function/Package/ETC_0_CostumePackage_PC_F.png",
    "class": 0
  }
]