[
  {
    "id": 210192021,
    "slotType": 12,
    "inventoryType": 2,
    "gainType": 0,
    "icon": "GUI/Icon/Item/Costume/PC_J/PC_J_EQ_EnemyFesta2_HairAcc01_01.png",
    "class": 10
  },
  {
    "id": 210192111,
    "slotType": 19,
    "inventoryType": 2,
    "gainType": 0,
    "icon": "GUI/Icon/Item/Costume/PC_J/PC_J_EQ_EnemyFesta2_Socks_11.png",
    "class": 10
  },
  {
    "id": 210192121,
    "slotType": 20,
    "inventoryType": 2,
    "gainType": 0,
    "icon": "GUI/Icon/Item/Costume/PC_J/PC_J_EQ_EnemyFesta2_Shoes_12.png",
    "class": 10
  },
  {
    "id": 210192131,
    "slotType": 23,
    "inventoryType": 2,
    "gainType": 0,
    "icon": "GUI/Icon/Item/Costume/PC_J/PC_J_EQ_EnemyFesta2_Tail_13.png",
    "class": 10
  },
  {
    "id": 839110041,
    "slotType": 251,
    "inventoryType": 13,
    "gainType": 0,
    "icon": "GUI/Icon/Item/Costume/PC_J/PC_J_EQ_CashHair34_Hair_32.png",
    "class": 10
  },
  {
    "id": 839310032,
    "slotType": 253,
    "inventoryType": 13,
    "gainType": 0,
    "icon": "GUI/Icon/Item/Appearance/Color/PC_J_EQ_EnemyFesta2_Eye_color_12.png",
    "class": 10
  },
  {
    "id": 210024141,
    "slotType": 21,
    "inventoryType": 2,
    "gainType": 0,
    "icon": "GUI/Icon/Item/Costume/PC_J/PC_J_WPAV_024.png",
    "class": 10
  },
  {
    "id": 810192091,
    "slotType": 0,
    "inventoryType": 13,
    "gainType": 0,
    "icon": "GUI/Icon/Item/Function/Package/PackageBox.png",
    "class": 10
  },
  {
    "id": 810192051,
    "slotType": 0,
    "inventoryType": 13,
    "gainType": 0,
    "icon": "GUI/Icon/Item/Function/Package/PackageBox.png",
    "class": 10
  },
  {
    "id": 810192021,
    "slotType": 0,
    "inventoryType": 13,
    "gainType": 0,
    "icon": "GUI/Icon/Item/Function/Package/PackageBox.png",
    "class": 10
  },
  {
    "id": 810192111,
    "slotType": 0,
    "inventoryType": 13,
    "gainType": 0,
    "icon": "GUI/Icon/Item/Function/Package/PackageBox.png",
    "class": 10
  },
  {
    "id": 810192121,
    "slotType": 0,
    "inventoryType": 13,
    "gainType": 0,
    "icon": "GUI/Icon/Item/Function/Package/PackageBox.png",
    "class": 10
  },
  {
    "id": 810192131,
    "slotType": 0,
    "inventoryType": 13,
    "gainType": 0,
    "icon": "GUI/Icon/Item/Function/Package/PackageBox.png",
    "class": 10
  },
  {
    "id": 810024141,
    "slotType": 0,
    "inventoryType": 13,
    "gainType": 0,
    "icon": "GUI/Icon/Item/Function/Package/PackageBox.png",
    "class": 10
  },
  {
    "id": 810192072,
    "slotType": 0,
    "inventoryType": 13,
    "gainType": 0,
    "icon": "GUI/Icon/Item/Function/Package/ETC_0_CostumePackage_PC_J.png",
    "class": 10
  },
  {
    "id": 910192072,
    "slotType": 0,
    "inventoryType": 13,
    "gainType": 0,
    "icon": "GUI/Icon/Item/Function/Package/ETC_0_CostumePackage_PC_J.png",
    "class": 10
  },
  {
    "id": 201645091,
    "slotType": 17,
    "inventoryType": 2,
    "gainType": 0,
    "icon": "GUI/Icon/Item/Costume/PC_A/PC_A_EQ_SwimmingSuit2_Costume03_09.png",
    "class": 1
  },
  {
    "id": 202620081,
    "slotType": 22,
    "inventoryType": 2,
    "gainType": 0,
    "icon": "GUI/Icon/Item/Costume/PC_B/PC_B_EQ_SwimmingSuit2_Costume02_08.png",
    "class": 2
  },
  {
    "id": 203644091,
    "slotType": 17,
    "inventoryType": 2,
    "gainType": 0,
    "icon": "GUI/Icon/Item/Costume/PC_C/PC_C_EQ_SwimmingSuit2_Costume03_09.png",
    "class": 3
  },
  {
    "id": 204621081,
    "slotType": 22,
    "inventoryType": 2,
    "gainType": 0,
    "icon": "GUI/Icon/Item/Costume/PC_D/PC_D_EQ_SwimmingSuit2_Costume02_08.png",
    "class": 4
  },
  {
    "id": 205639091,
    "slotType": 17,
    "inventoryType": 2,
    "gainType": 0,
    "icon": "GUI/Icon/Item/Costume/PC_E/PC_E_EQ_SwimmingSuit2_Costume03_09.png",
    "class": 5
  },
  {
    "id": 206636091,
    "slotType": 17,
    "inventoryType": 2,
    "gainType": 0,
    "icon": "GUI/Icon/Item/Costume/PC_F/PC_F_EQ_SwimmingSuit2_Costume03_09.png",
    "class": 6
  },
  {
    "id": 207342091,
    "slotType": 17,
    "inventoryType": 2,
    "gainType": 0,
    "icon": "GUI/Icon/Item/Costume/PC_G/PC_G_EQ_SwimmingSuit2_Costume03_09.png",
    "class": 7
  },
  {
    "id": 208356091,
    "slotType": 17,
    "inventoryType": 2,
    "gainType": 0,
    "icon": "GUI/Icon/Item/Costume/PC_H/PC_H_EQ_SwimmingSuit2_Costume03_09.png",
    "class": 8
  },
  {
    "id": 209328091,
    "slotType": 17,
    "inventoryType": 2,
    "gainType": 0,
    "icon": "GUI/Icon/Item/Costume/PC_I/PC_I_EQ_SwimmingSuit2_Costume03_09.png",
    "class": 9
  },
  {
    "id": 210193091,
    "slotType": 17,
    "inventoryType": 2,
    "gainType": 0,
    "icon": "GUI/Icon/Item/Costume/PC_J/PC_J_EQ_SwimmingSuit2_Costume03_09.png",
    "class": 10
  },
  {
    "id": 890110056,
    "slotType": 0,
    "inventoryType": 13,
    "gainType": 0,
    "icon": "GUI/Icon/Item/Etc/ETC_0_PhotoAlbum.png",
    "class": 1
  },
  {
    "id": 890210056,
    "slotType": 0,
    "inventoryType": 13,
    "gainType": 0,
    "icon": "GUI/Icon/Item/Etc/ETC_0_PhotoAlbum.png",
    "class": 2
  },
  {
    "id": 890310056,
    "slotType": 0,
    "inventoryType": 13,
    "gainType": 0,
    "icon": "GUI/Icon/Item/Etc/ETC_0_PhotoAlbum.png",
    "class": 3
  },
  {
    "id": 890410056,
    "slotType": 0,
    "inventoryType": 13,
    "gainType": 0,
    "icon": "GUI/Icon/Item/Etc/ETC_0_PhotoAlbum.png",
    "class": 4
  },
  {
    "id": 890510056,
    "slotType": 0,
    "inventoryType": 13,
    "gainType": 0,
    "icon": "GUI/Icon/Item/Etc/ETC_0_PhotoAlbum.png",
    "class": 5
  },
  {
    "id": 890610056,
    "slotType": 0,
    "inventoryType": 13,
    "gainType": 0,
    "icon": "GUI/Icon/Item/Etc/ETC_0_PhotoAlbum.png",
    "class": 6
  },
  {
    "id": 890710056,
    "slotType": 0,
    "inventoryType": 13,
    "gainType": 0,
    "icon": "GUI/Icon/Item/Etc/ETC_0_PhotoAlbum.png",
    "class": 7
  },
  {
    "id": 890810056,
    "slotType": 0,
    "inventoryType": 13,
    "gainType": 0,
    "icon": "GUI/Icon/Item/Etc/ETC_0_PhotoAlbum.png",
    "class": 8
  },
  {
    "id": 890910056,
    "slotType": 0,
    "inventoryType": 13,
    "gainType": 0,
    "icon": "GUI/Icon/Item/Etc/ETC_0_PhotoAlbum.png",
    "class": 9
  },
  {
    "id": 891010056,
    "slotType": 0,
    "inventoryType": 13,
    "gainType": 0,
    "icon": "GUI/Icon/Item/Etc/ETC_0_PhotoAlbum.png",
    "class": 0
  },
  {
    "id": 890100056,
    "slotType": 0,
    "inventoryType": 13,
    "gainType": 0,
    "icon": "GUI/Icon/Item/Cash/ETC_0_CashPhotoAlbum.png",
    "class": 1
  },
  {
    "id": 890200056,
    "slotType": 0,
    "inventoryType": 13,
    "gainType": 0,
    "icon": "GUI/Icon/Item/Cash/ETC_0_CashPhotoAlbum.png",
    "class": 2
  },
  {
    "id": 890300056,
    "slotType": 0,
    "inventoryType": 13,
    "gainType": 0,
    "icon": "GUI/Icon/Item/Cash/ETC_0_CashPhotoAlbum.png",
    "class": 3
  },
  {
    "id": 890400056,
    "slotType": 0,
    "inventoryType": 13,
    "gainType": 0,
    "icon": "GUI/Icon/Item/Cash/ETC_0_CashPhotoAlbum.png",
    "class": 4
  },
  {
    "id": 890500056,
    "slotType": 0,
    "inventoryType": 13,
    "gainType": 0,
    "icon": "GUI/Icon/Item/Cash/ETC_0_CashPhotoAlbum.png",
    "class": 5
  },
  {
    "id": 890600056,
    "slotType": 0,
    "inventoryType": 13,
    "gainType": 0,
    "icon": "GUI/Icon/Item/Cash/ETC_0_CashPhotoAlbum.png",
    "class": 6
  },
  {
    "id": 890700056,
    "slotType": 0,
    "inventoryType": 13,
    "gainType": 0,
    "icon": "GUI/Icon/Item/Cash/ETC_0_CashPhotoAlbum.png",
    "class": 7
  },
  {
    "id": 890800056,
    "slotType": 0,
    "inventoryType": 13,
    "gainType": 0,
    "icon": "GUI/Icon/Item/Cash/ETC_0_CashPhotoAlbum.png",
    "class": 8
  },
  {
    "id": 890900056,
    "slotType": 0,
    "inventoryType": 13,
    "gainType": 0,
    "icon": "GUI/Icon/Item/Cash/ETC_0_CashPhotoAlbum.png",
    "class": 9
  },
  {
    "id": 891000056,
    "slotType": 0,
    "inventoryType": 13,
    "gainType": 0,
    "icon": "GUI/Icon/Item/Cash/ETC_0_CashPhotoAlbum.png",
    "class": 10
  },
  {
    "id": 801644073,
    "slotType": 0,
    "inventoryType": 13,
    "gainType": 0,
    "icon": "GUI/Icon/Item/Function/Package/ETC_0_CostumePackage_PC_A.png",
    "class": 1
  },
  {
    "id": 802619073,
    "slotType": 0,
    "inventoryType": 13,
    "gainType": 0,
    "icon": "GUI/Icon/Item/Function/Package/ETC_0_CostumePackage_PC_B.png",
    "class": 2
  },
  {
    "id": 803643073,
    "slotType": 0,
    "inventoryType": 13,
    "gainType": 0,
    "icon": "GUI/Icon/Item/Function/Package/ETC_0_CostumePackage_PC_C.png",
    "class": 3
  },
  {
    "id": 804620073,
    "slotType": 0,
    "inventoryType": 13,
    "gainType": 0,
    "icon": "GUI/Icon/Item/Function/Package/ETC_0_CostumePackage_PC_D.png",
    "class": 4
  },
  {
    "id": 805638073,
    "slotType": 0,
    "inventoryType": 13,
    "gainType": 0,
    "icon": "GUI/Icon/Item/Function/Package/ETC_0_CostumePackage_PC_E.png",
    "class": 5
  },
  {
    "id": 806635073,
    "slotType": 0,
    "inventoryType": 13,
    "gainType": 0,
    "icon": "GUI/Icon/Item/Function/Package/ETC_0_CostumePackage_PC_F.png",
    "class": 6
  },
  {
    "id": 807341073,
    "slotType": 0,
    "inventoryType": 13,
    "gainType": 0,
    "icon": "GUI/Icon/Item/Function/Package/ETC_0_CostumePackage_PC_G.png",
    "class": 7
  },
  {
    "id": 808355073,
    "slotType": 0,
    "inventoryType": 13,
    "gainType": 0,
    "icon": "GUI/Icon/Item/Function/Package/ETC_0_CostumePackage_PC_H.png",
    "class": 8
  },
  {
    "id": 809327073,
    "slotType": 0,
    "inventoryType": 13,
    "gainType": 0,
    "icon": "GUI/Icon/Item/Function/Package/ETC_0_CostumePackage_PC_I.png",
    "class": 9
  },
  {
    "id": 810192073,
    "slotType": 0,
    "inventoryType": 13,
    "gainType": 0,
    "icon": "GUI/Icon/Item/Function/Package/ETC_0_CostumePackage_PC_J.png",
    "class": 10
  },
  {
    "id": 991000737,
    "slotType": 0,
    "inventoryType": 13,
    "gainType": 0,
    "icon": "GUI/Icon/Item/Function/Package/PackageBox.png",
    "class": 0
  },
  {
    "id": 991000738,
    "slotType": 0,
    "inventoryType": 13,
    "gainType": 0,
    "icon": "GUI/Icon/Item/Function/Package/PackageBox.png",
    "class": 0
  },
  {
    "id": 906077000,
    "slotType": 0,
    "inventoryType": 0,
    "gainType": 2,
    "icon": "GUI/Icon/Item/Event/Event_Summer_NightOrb.png",
    "class": 0
  },
  {
    "id": 906077001,
    "slotType": 0,
    "inventoryType": 0,
    "gainType": 2,
    "icon": "GUI/Icon/Item/Event/Event_Lanterns_Red.png",
    "class": 0
  },
  {
    "id": 906077002,
    "slotType": 0,
    "inventoryType": 0,
    "gainType": 2,
    "icon": "GUI/Icon/Item/Event/Event_Lanterns_Blue.png",
    "class": 0
  },
  {
    "id": 906077003,
    "slotType": 0,
    "inventoryType": 13,
    "gainType": 0,
    "icon": "GUI/Icon/Item/Etc/ETC_0_EnergyConverter.png",
    "class": 0
  },
  {
    "id": 906077004,
    "slotType": 0,
    "inventoryType": 13,
    "gainType": 0,
    "icon": "GUI/Icon/Item/Cash/QBD.png",
    "class": 0
  },
  {
    "id": 906077005,
    "slotType": 0,
    "inventoryType": 0,
    "gainType": 0,
    "icon": "GUI/Icon/Item/Etc/ETC_0_TitleItem.png",
    "class": 0
  },
  {
    "id": 906077006,
    "slotType": 0,
    "inventoryType": 0,
    "gainType": 0,
    "icon": "GUI/Icon/Item/Etc/ETC_0_TitleItem.png",
    "class": 0
  },
  {
    "id": 906077007,
    "slotType": 0,
    "inventoryType": 0,
    "gainType": 0,
    "icon": "GUI/Icon/Item/Function/Package/ETC_0_CostumePackage.png",
    "class": 0
  },
  {
    "id": 906077008,
    "slotType": 0,
    "inventoryType": 0,
    "gainType": 0,
    "icon": "GUI/Icon/Item/Function/Package/ETC_0_DyeCostumePackage.png",
    "class": 0
  },
  {
    "id": 906077009,
    "slotType": 0,
    "inventoryType": 0,
    "gainType": 0,
    "icon": "",
    "class": 1
  },
  {
    "id": 906077010,
    "slotType": 0,
    "inventoryType": 0,
    "gainType": 0,
    "icon": "",
    "class": 2
  },
  {
    "id": 906077011,
    "slotType": 0,
    "inventoryType": 0,
    "gainType": 0,
    "icon": "",
    "class": 3
  },
  {
    "id": 906077012,
    "slotType": 0,
    "inventoryType": 0,
    "gainType": 0,
    "icon": "",
    "class": 4
  },
  {
    "id": 906077013,
    "slotType": 0,
    "inventoryType": 0,
    "gainType": 0,
    "icon": "",
    "class": 5
  },
  {
    "id": 906077014,
    "slotType": 0,
    "inventoryType": 0,
    "gainType": 0,
    "icon": "",
    "class": 6
  },
  {
    "id": 906077015,
    "slotType": 0,
    "inventoryType": 0,
    "gainType": 0,
    "icon": "",
    "class": 7
  },
  {
    "id": 906077016,
    "slotType": 0,
    "inventoryType": 0,
    "gainType": 0,
    "icon": "",
    "class": 8
  },
  {
    "id": 906077017,
    "slotType": 0,
    "inventoryType": 0,
    "gainType": 0,
    "icon": "",
    "class": 9
  },
  {
    "id": 906077018,
    "slotType": 0,
    "inventoryType": 0,
    "gainType": 0,
    "icon": "",
    "class": 10
  },
  {
    "id": 906077019,
    "slotType": 0,
    "inventoryType": 0,
    "gainType": 0,
    "icon": "GUI/Icon/Item/Function/Package/ETC_0_CostumePackage.png",
    "class": 0
  },
  {
    "id": 906077020,
    "slotType": 0,
    "inventoryType": 0,
    "gainType": 0,
    "icon": "",
    "class": 1
  },
  {
    "id": 906077021,
    "slotType": 0,
    "inventoryType": 0,
    "gainType": 0,
    "icon": "",
    "class": 2
  },
  {
    "id": 906077022,
    "slotType": 0,
    "inventoryType": 0,
    "gainType": 0,
    "icon": "",
    "class": 3
  },
  {
    "id": 906077023,
    "slotType": 0,
    "inventoryType": 0,
    "gainType": 0,
    "icon": "",
    "class": 4
  },
  {
    "id": 906077024,
    "slotType": 0,
    "inventoryType": 0,
    "gainType": 0,
    "icon": "",
    "class": 5
  },
  {
    "id": 906077025,
    "slotType": 0,
    "inventoryType": 0,
    "gainType": 0,
    "icon": "",
    "class": 6
  },
  {
    "id": 906077026,
    "slotType": 0,
    "inventoryType": 0,
    "gainType": 0,
    "icon": "",
    "class": 7
  },
  {
    "id": 906077027,
    "slotType": 0,
    "inventoryType": 0,
    "gainType": 0,
    "icon": "",
    "class": 8
  },
  {
    "id": 906077028,
    "slotType": 0,
    "inventoryType": 0,
    "gainType": 0,
    "icon": "",
    "class": 9
  },
  {
    "id": 906077029,
    "slotType": 0,
    "inventoryType": 0,
    "gainType": 0,
    "icon": "",
    "class": 10
  },
  {
    "id": 906077030,
    "slotType": 0,
    "inventoryType": 0,
    "gainType": 0,
    "icon": "GUI/Icon/Item/Function/Package/RandomBox.png",
    "class": 0
  },
  {
    "id": 906077031,
    "slotType": 0,
    "inventoryType": 0,
    "gainType": 0,
    "icon": "GUI/Icon/Item/Function/Package/PackageBox.png",
    "class": 0
  },
  {
    "id": 906077032,
    "slotType": 0,
    "inventoryType": 0,
    "gainType": 0,
    "icon": "GUI/Icon/Item/Function/Package/PackageBox.png",
    "class": 0
  },
  {
    "id": 801644074,
    "slotType": 0,
    "inventoryType": 13,
    "gainType": 0,
    "icon": "GUI/Icon/Item/Function/Package/ETC_0_CostumePackage_PC_A.png",
    "class": 1
  },
  {
    "id": 802619074,
    "slotType": 0,
    "inventoryType": 13,
    "gainType": 0,
    "icon": "GUI/Icon/Item/Function/Package/ETC_0_CostumePackage_PC_B.png",
    "class": 2
  },
  {
    "id": 803643074,
    "slotType": 0,
    "inventoryType": 13,
    "gainType": 0,
    "icon": "GUI/Icon/Item/Function/Package/ETC_0_CostumePackage_PC_C.png",
    "class": 3
  },
  {
    "id": 804620074,
    "slotType": 0,
    "inventoryType": 13,
    "gainType": 0,
    "icon": "GUI/Icon/Item/Function/Package/ETC_0_CostumePackage_PC_D.png",
    "class": 4
  },
  {
    "id": 805638074,
    "slotType": 0,
    "inventoryType": 13,
    "gainType": 0,
    "icon": "GUI/Icon/Item/Function/Package/ETC_0_CostumePackage_PC_E.png",
    "class": 5
  },
  {
    "id": 806635074,
    "slotType": 0,
    "inventoryType": 13,
    "gainType": 0,
    "icon": "GUI/Icon/Item/Function/Package/ETC_0_CostumePackage_PC_F.png",
    "class": 6
  },
  {
    "id": 807341074,
    "slotType": 0,
    "inventoryType": 13,
    "gainType": 0,
    "icon": "GUI/Icon/Item/Function/Package/ETC_0_CostumePackage_PC_G.png",
    "class": 7
  },
  {
    "id": 808355074,
    "slotType": 0,
    "inventoryType": 13,
    "gainType": 0,
    "icon": "GUI/Icon/Item/Function/Package/ETC_0_CostumePackage_PC_H.png",
    "class": 8
  },
  {
    "id": 809327074,
    "slotType": 0,
    "inventoryType": 13,
    "gainType": 0,
    "icon": "GUI/Icon/Item/Function/Package/ETC_0_CostumePackage_PC_I.png",
    "class": 9
  }
]